{
  "annotations": {
    "changelogDate": "20240524180849"
  },
  "applications": ["microserviceGIR"],
  "clientRootFolder": "microserviceGIR",
  "databaseType": "sql",
  "dto": "mapstruct",
  "entityTableName": "type_bourse",
  "fields": [
    {
      "fieldName": "libelleTypeBourse",
      "fieldType": "String",
      "fieldValidateRules": ["required", "unique"]
    }
  ],
  "microserviceName": "microserviceGIR",
  "name": "TypeBourse",
  "pagination": "pagination",
  "relationships": [],
  "searchEngine": "no",
  "service": "serviceImpl"
}
